opentelemetry/instrumentation/openai/__init__.py
opentelemetry/instrumentation/openai/package.py
opentelemetry/instrumentation/openai/version.py
opentelemetry_instrument_openai-0.7.1.dist-info/LICENSE.md
opentelemetry_instrument_openai-0.7.1.dist-info/METADATA
opentelemetry_instrument_openai-0.7.1.dist-info/WHEEL
opentelemetry_instrument_openai-0.7.1.dist-info/entry_points.txt
opentelemetry_instrument_openai-0.7.1.dist-info/RECORD
