Metadata-Version: 2.1
Name: opentelemetry-instrument-openai
Version: 0.7.1
Summary: OpenTelemetry openai instrumentation
License: Apache-2.0
Author: cartermp
Author-email: pcarter@fastmail.com
Maintainer: cartermp
Maintainer-email: pcarter@fastmail.com
Requires-Python: >=3.7.1,<4.0
Classifier: License :: OSI Approved :: Apache Software License
Classifier: Programming Language :: Python :: 3
Classifier: Programming Language :: Python :: 3.8
Classifier: Programming Language :: Python :: 3.9
Classifier: Programming Language :: Python :: 3.10
Classifier: Programming Language :: Python :: 3.11
Classifier: Programming Language :: Python :: 3.12
Provides-Extra: instruments
Requires-Dist: openai (>=0.27.8,<0.28.0) ; extra == "instruments"
Requires-Dist: opentelemetry-api (>=1.18.0)
Requires-Dist: opentelemetry-instrumentation (>=0.39b0)
Requires-Dist: opentelemetry-semantic-conventions (>=0.39b0)
Requires-Dist: wrapt (>=1.15.0,<2.0.0)
